{"trial_id": "b3bfb2d82faea4c72c43c23d0cc3c48b", "hyperparameters": {"space": [{"class_name": "Int", "config": {"name": "units", "default": null, "conditions": [], "min_value": 10, "max_value": 100, "step": 10, "sampling": null}}, {"class_name": "Choice", "config": {"name": "learning_rate", "default": 0.1, "conditions": [], "values": [0.1, 0.01, 0.001, 0.0001, 0.05, 0.005, 0.0005], "ordered": true}}], "values": {"units": 20, "learning_rate": 0.1, "tuner/epochs": 10, "tuner/initial_epoch": 4, "tuner/bracket": 2, "tuner/round": 2, "tuner/trial_id": "efb8f642a29f05067404a13f53a82e96"}}, "metrics": {"metrics": {"loss": {"direction": "min", "observations": [{"value": [0.23983092606067657], "step": 0}]}, "mae": {"direction": "min", "observations": [{"value": [0.23983092606067657], "step": 0}]}, "val_loss": {"direction": "min", "observations": [{"value": [0.19370347261428833], "step": 0}]}, "val_mae": {"direction": "min", "observations": [{"value": [0.19370347261428833], "step": 0}]}}}, "score": 0.23983092606067657, "best_step": 0, "status": "COMPLETED"}